authservice_django/__init__.py
authservice_django/backends.py
authservice_django/client.py
authservice_django/config.py
authservice_django/decorators.py
authservice_django/exceptions.py
authservice_django/middleware.py
authservice_django/mixins.py
authservice_django/drf/__init__.py
authservice_django/drf/authentication.py
authservice_django/drf/permissions.py
authservice_django-1.0.0.dist-info/METADATA
authservice_django-1.0.0.dist-info/WHEEL
authservice_django-1.0.0.dist-info/top_level.txt
authservice_django-1.0.0.dist-info/RECORD
