Metadata-Version: 2.4
Name: authservice-django
Version: 1.0.0
Summary: Django SDK for Auth Service
Home-page: https://github.com/hasnain3033/django-auth-sdk
Author: hasnain3033
Author-email: Auth Service Team <support@authservice.com>
License: MIT
Keywords: django,authentication,authorization,rbac,permissions
Requires-Python: >=3.8
Requires-Dist: django>=3.2
Requires-Dist: requests>=2.28.0
Requires-Dist: pyjwt>=2.8.0
Requires-Dist: cryptography>=41.0.0
Provides-Extra: drf
Requires-Dist: djangorestframework>=3.12.0; extra == "drf"
Provides-Extra: async
Requires-Dist: httpx>=0.24.0; extra == "async"
Provides-Extra: dev
Requires-Dist: pytest>=7.0.0; extra == "dev"
Requires-Dist: pytest-django>=4.5.0; extra == "dev"
Requires-Dist: pytest-cov>=4.0.0; extra == "dev"
Requires-Dist: black>=23.0.0; extra == "dev"
Requires-Dist: mypy>=1.0.0; extra == "dev"
Requires-Dist: django-stubs>=4.2.0; extra == "dev"
Dynamic: author
Dynamic: home-page
Dynamic: requires-python
